Workbook

Sheet Objectif
A1: OBJECTIF ANNUEL
C2: Total
A3: Période | C3: 2025 | D3: 2026 | F3: Objectif | G3: % atteint | K3: Vente de l'année | L3: =D16 -> 8080
A4: JANVIER | C4: =C21+G21+K21+O21+S21+W21 -> 0 | D4: =Janvier!B4 -> 0 | F4: =E21+I21+M21+Q21+U21+Y21 -> 0 | G4: =D4/F4 -> #DIV/0!
A5: FÉVRIER | C5: =C22+G22+K22+O22+S22+W22 -> 0 | D5: ='Février'!B4 -> 1195 | F5: =E22+I22+M22+Q22+U22+Y22 -> 0 | G5: =D5/F5 -> #DIV/0! | K5: Objectif de vente annuel | L5: =E33+I33+M33+Q33+U33+Y33 -> 439000
A6: MARS | C6: =C23+G23+K23+O23+S23+W23 -> 0 | D6: =Mars!B4 -> 3040 | F6: =E23+I23+M23+Q23+U23+Y23 -> 0 | G6: =D6/F6 -> #DIV/0!
A7: AVRIL | C7: =C24+G24+K24+O24+S24+W24 -> 0 | D7: =Avril!B4 -> 3845 | F7: =E24+I24+M24+Q24+U24+Y24 -> 22500 | G7: =D7/F7 -> 0.17088889 | K7: % atteint | L7: =L3/L5 -> 0.018405467
A8: MAI | C8: =C25+G25+K25+O25+S25+W25 -> 0 | D8: =Mai!B4 -> 0 | F8: =E25+I25+M25+Q25+U25+Y25 -> 41500 | G8: =D8/F8 -> 0
A9: JUIN | C9: =C26+G26+K26+O26+S26+W26 -> 0 | D9: =Juin!B4 -> 0 | F9: =E26+I26+M26+Q26+U26+Y26 -> 49000 | G9: =D9/F9 -> 0
A10: JUILLET | C10: =C27+G27+K27+O27+S27+W27 -> 0 | D10: =Juillet!B4 -> 0 | F10: =E27+I27+M27+Q27+U27+Y27 -> 32000 | G10: =D10/F10 -> 0
A11: AOÛT | C11: =C28+G28+K28+O28+S28+W28 -> 0 | D11: ='Août'!B4 -> 0 | F11: =E28+I28+M28+Q28+U28+Y28 -> 54000 | G11: =D11/F11 -> 0
A12: SEPTEMBRE | C12: =C29+G29+K29+O29+S29+W29 -> 0 | D12: =Septembre!B4 -> 0 | F12: =E29+I29+M29+Q29+U29+Y29 -> 76000 | G12: =D12/F12 -> 0
A13: OCTOBRE | C13: =C30+G30+K30+O30+S30+W30 -> 0 | D13: =Octobre!B4 -> 0 | F13: =E30+I30+M30+Q30+U30+Y30 -> 76000 | G13: =D13/F13 -> 0
A14: NOVEMBRE | C14: =C31+G31+K31+O31+S31+W31 -> 0 | D14: =Novembre!B4 -> 0 | F14: =E31+I31+M31+Q31+U31+Y31 -> 59000 | G14: =D14/F14 -> 0
A15: DÉCEMBRE | C15: =C32+G32+K32+O32+S32+W32 -> 0 | D15: ='Décembre'!B4 -> 0 | F15: =E32+I32+M32+Q32+U32+Y32 -> 29000 | G15: =D15/F15 -> 0
A16: Total | C16: =SUM(C4:C15) -> 0 | D16: =SUM(D4:D15) -> 8080 | F16: =SUM(F4:F15) -> 439000 | G16: =D16/F16 -> 0.018405467
C19: MULTI-ANNONCEURS | G19: PROMOTIONNEL | K19: DIST. PUBLICITAIRE SOLO | O19: NUMÉRIQUE | S19: APPLICATION | W19: SERVICES IA
A20: Période | C20: 2025 | D20: 2026 | E20: Objectif | F20: % atteint | G20: 2025 | H20: 2026 | I20: Objectif | J20: % atteint | K20: 2025 | L20: 2026 | M20: Objectif | N20: % atteint | O20: 2025 | P20: 2026 | Q20: Objectif | R20: % atteint | S20: 2025 | T20: 2026 | U20: Objectif | V20: % atteint | W20: 2025 | X20: 2026 | Y20: Objectif | Z20: % atteint
A21: JANVIER | D21: =Janvier!C4 -> 0 | E21: 0 | F21: =D21/E21 -> #DIV/0! | H21: =Janvier!D4 -> 0 | I21: 0 | J21: =H21/I21 -> #DIV/0! | L21: =Janvier!E4 -> 0 | M21: 0 | N21: =L21/M21 -> #DIV/0! | P21: =Janvier!F4 -> 0 | Q21: 0 | R21: =P21/Q21 -> #DIV/0! | T21: =Janvier!G4 -> 0 | V21: =T21/U21 -> #DIV/0! | X21: =Janvier!K4 | Z21: =X21/Y21 -> #DIV/0!
A22: FÉVRIER | D22: ='Février'!C4 -> 1195 | E22: 0 | F22: =D22/E22 -> #DIV/0! | H22: ='Février'!D4 -> 0 | I22: 0 | J22: =H22/I22 -> #DIV/0! | L22: ='Février'!E4 -> 0 | M22: 0 | N22: =L22/M22 -> #DIV/0! | P22: ='Février'!F4 -> 0 | Q22: 0 | R22: =P22/Q22 -> #DIV/0! | T22: ='Février'!G4 -> 0 | V22: =T22/U22 -> #DIV/0! | X22: ='Février'!K4 | Z22: =X22/Y22 -> #DIV/0!
A23: MARS | D23: =Mars!C4 -> 1195 | E23: 0 | F23: =D23/E23 -> #DIV/0! | H23: =Mars!D4 -> 0 | I23: 0 | J23: =H23/I23 -> #DIV/0! | L23: =Mars!E4 -> 1435 | M23: 0 | N23: =L23/M23 -> #DIV/0! | P23: =Mars!F4 -> 410 | Q23: 0 | R23: =P23/Q23 -> #DIV/0! | T23: =Mars!G4 -> 0 | V23: =T23/U23 -> #DIV/0! | X23: =Mars!K4 | Z23: =X23/Y23 -> #DIV/0!
A24: AVRIL | D24: =Avril!C4 -> 3685 | E24: =30000*0.5 -> 15000 | F24: =D24/E24 -> 0.24566667 | H24: =Avril!D4 -> 0 | I24: =2000*0.5 -> 1000 | J24: =H24/I24 -> 0 | L24: =Avril!E4 -> 0 | M24: =10000*0.5 -> 5000 | N24: =L24/M24 -> 0 | P24: =Avril!F4 -> 160 | Q24: 1500 | R24: =P24/Q24 -> 0.10666667 | T24: =Avril!G4 -> 0 | V24: =T24/U24 -> #DIV/0! | X24: =Avril!K4 | Z24: =X24/Y24 -> #DIV/0!
A25: MAI | D25: =Mai!C4 -> 0 | E25: =40000*0.75 -> 30000 | F25: =D25/E25 -> 0 | H25: =Mai!D4 -> 0 | I25: 2000 | J25: =H25/I25 -> 0 | L25: =Mai!E4 -> 0 | M25: =10000*0.75 -> 7500 | N25: =L25/M25 -> 0 | P25: =Mai!F4 -> 0 | Q25: 2000 | R25: =P25/Q25 -> 0 | T25: =Mai!G4 -> 0 | V25: =T25/U25 -> #DIV/0! | X25: =Mai!K4 | Z25: =X25/Y25 -> #DIV/0!
A26: JUIN | D26: =Juin!C4 -> 0 | E26: 40000 | F26: =D26/E26 -> 0 | H26: =Juin!D4 -> 0 | I26: 2000 | J26: =H26/I26 -> 0 | L26: =Juin!E4 -> 0 | M26: 5000 | N26: =L26/M26 -> 0 | P26: =Juin!F4 -> 0 | Q26: 2000 | R26: =P26/Q26 -> 0 | T26: =Juin!G4 -> 0 | V26: =T26/U26 -> #DIV/0! | X26: =Juin!K4 | Z26: =X26/Y26 -> #DIV/0!
A27: JUILLET | D27: =Juillet!C4 -> 0 | E27: 25000 | F27: =D27/E27 -> 0 | H27: =Juillet!D4 -> 0 | I27: 2000 | J27: =H27/I27 -> 0 | L27: =Juillet!E4 -> 0 | M27: 3000 | N27: =L27/M27 -> 0 | P27: =Juillet!F4 -> 0 | Q27: 2000 | R27: =P27/Q27 -> 0 | T27: =Juillet!G4 -> 0 | V27: =T27/U27 -> #DIV/0! | X27: =Juillet!K4 | Z27: =X27/Y27 -> #DIV/0!
A28: AOÛT | D28: ='Août'!C4 -> 0 | E28: 40000 | F28: =D28/E28 -> 0 | H28: ='Août'!D4 -> 0 | I28: 2000 | J28: =H28/I28 -> 0 | L28: ='Août'!E4 -> 0 | M28: 8000 | N28: =L28/M28 -> 0 | P28: ='Août'!F4 -> 0 | Q28: 4000 | R28: =P28/Q28 -> 0 | T28: ='Août'!G4 -> 0 | V28: =T28/U28 -> #DIV/0! | X28: ='Août'!K4 | Z28: =X28/Y28 -> #DIV/0!
A29: SEPTEMBRE | D29: =Septembre!C4 -> 0 | E29: 60000 | F29: =D29/E29 -> 0 | H29: =Septembre!D4 -> 0 | I29: 2000 | J29: =H29/I29 -> 0 | L29: =Septembre!E4 -> 0 | M29: 10000 | N29: =L29/M29 -> 0 | P29: =Septembre!F4 -> 0 | Q29: 4000 | R29: =P29/Q29 -> 0 | T29: =Septembre!G4 -> 0 | V29: =T29/U29 -> #DIV/0! | X29: =Septembre!K4 | Z29: =X29/Y29 -> #DIV/0!
A30: OCTOBRE | D30: =Octobre!C4 -> 0 | E30: 60000 | F30: =D30/E30 -> 0 | H30: =Octobre!D4 -> 0 | I30: 2000 | J30: =H30/I30 -> 0 | L30: =Octobre!E4 -> 0 | M30: 10000 | N30: =L30/M30 -> 0 | P30: =Octobre!F4 -> 0 | Q30: 4000 | R30: =P30/Q30 -> 0 | T30: =Octobre!G4 -> 0 | V30: =T30/U30 -> #DIV/0! | X30: =Octobre!K4 | Z30: =X30/Y30 -> #DIV/0!
A31: NOVEMBRE | D31: =Novembre!C4 -> 0 | E31: 45000 | F31: =D31/E31 -> 0 | H31: =Novembre!D4 -> 0 | I31: 2000 | J31: =H31/I31 -> 0 | L31: =Novembre!E4 -> 0 | M31: 8000 | N31: =L31/M31 -> 0 | P31: =Novembre!F4 -> 0 | Q31: 4000 | R31: =P31/Q31 -> 0 | T31: =Novembre!G4 -> 0 | V31: =T31/U31 -> #DIV/0! | X31: =Novembre!K4 | Z31: =X31/Y31 -> #DIV/0!
A32: DÉCEMBRE | D32: ='Décembre'!C4 -> 0 | E32: 20000 | F32: =D32/E32 -> 0 | H32: 0 | I32: 2000 | J32: =H32/I32 -> 0 | L32: ='Décembre'!E4 -> 0 | M32: 3000 | N32: =L32/M32 -> 0 | P32: ='Décembre'!F4 -> 0 | Q32: 4000 | R32: =P32/Q32 -> 0 | T32: ='Décembre'!G4 -> 0 | V32: =T32/U32 -> #DIV/0! | X32: ='Décembre'!K4 | Z32: =X32/Y32 -> #DIV/0!
A33: Total | C33: =SUM(C21:C32) -> 0 | D33: =SUM(D21:D32) -> 6075 | E33: =SUM(E21:E32) -> 335000 | F33: =D33/E33 -> 0.018134328 | G33: =SUM(G21:G32) -> 0 | H33: =SUM(H21:H32) -> 0 | I33: =SUM(I21:I32) -> 17000 | J33: =H33/I33 -> 0 | K33: =SUM(K21:K32) -> 0 | L33: =SUM(L21:L32) -> 1435 | M33: =SUM(M21:M32) -> 59500 | N33: =L33/M33 -> 0.024117647 | O33: =SUM(O21:O32) -> 0 | P33: =SUM(P21:P32) -> 570 | Q33: =SUM(Q21:Q32) -> 27500 | R33: =P33/Q33 -> 0.020727273 | S33: =SUM(S21:S32) -> 0 | T33: =SUM(T21:T32) -> 0 | U33: =SUM(U21:U32) -> 0 | V33: =T33/U33 -> #DIV/0! | W33: =SUM(W21:W32) -> 0 | X33: =SUM(X21:X32) -> 0 | Y33: =SUM(Y21:Y32) -> 0 | Z33: =X33/Y33 -> #DIV/0!

Sheet Paye
A1: PAIEMENT AFFICHEZ | G1: SOLDE ANNÉE PRÉCÉDANTE
A2: PAYE # | B2: Salaire de base | C2: Commission | D2: Remboursement de dépenses | E2: Fériés | F2: Vacances
A3: 46086 | B3: 961.54
A4: 46100 | B4: 1538.46 | G4: MON BONUS ANNUEL | H4: 0
A5: 46114 | B5: 1923.07
A6: 46128 | B6: 1730.76 | E6: 192.31
A7: 46142 | B7: 1923.07 | C7: 1000
G9: COMMISSION 2025 FACTURÉES | H9: =Objectif!D16*0.05 -> 404
G11: MONTANT EN BANQUE | H11: =H1+H9-C29+I18 -> -596
G15: VACANCES ET FÉRIÉS | H15: VOIR SUR VOTRE TALON DE PAIE
G18: AUTRE (TOTAL) | I18: =SUM(I19:I47) -> 0
A29: SOMME | C29: =SUM(C3:C28) -> 1000 | D29: =SUM(D3:D28) -> 0 | E29: =SUM(E3:E28) -> 192.31 | F29: =SUM(F3:F28) -> 0

Sheet Janvier
B1: Totaux | C1: MÉDIA MULTI-ANNONCEURS | D1: PROMOTIONNEL | E1: DIST. PUBLICITAIRE SOLO | F1: NUMÉRIQUE | G1: APPLICATION | H1: SERVICES IA
A2: Commission | B2: =SUM(G7:G962) -> 0 | C2: =SUMIF(F8:F960,"MÉDIA MULTI-ANNONCEURS",G8:G960) -> 0 | D2: =SUMIF(F8:F960,"PROMOTIONNEL",G8:G960) -> 0 | E2: =SUMIF(F8:F960,"DIST. PUBLICITAIRE SOLO",G8:G960) -> 0 | F2: =SUMIF(F8:F960,"AGENCE PUB",G8:G960) -> 0 | G2: =SUMIF(F8:F960,"AGENCE WEB",G8:G960) -> 0 | H2: =SUMIF(F8:F960,"SERVICES IA",G8:G960) -> 0
A4: Vente | B4: =SUM(B8:B962) -> 0 | C4: =SUMIF(F8:F960,"MÉDIA MULTI-ANNONCEURS",B8:B960) -> 0 | D4: =SUMIF(F8:F960,"PROMOTIONNEL",B8:B960) -> 0 | E4: =SUMIF(F8:F960,"DIST. PUBLICITAIRE SOLO",B8:B960) -> 0 | F4: =SUMIF(F8:F960,"AGENCE PUB",B8:B960) -> 0 | G4: =SUMIF(F8:F960,"AGENCE WEB",B8:B960) -> 0 | H4: =SUMIF(F8:F960,"SERVICES IA",B8:B960) -> 0
A7: CLIENT | B7: TOTAL (AVANT TAXES) | C7: # FACTURE | D7: DATE | E7: REPRÉSENTANT | F7: DÉPARTEMENT | G7: COMMISSION
G8: =B8*0.05 -> 0
G9: =B9*0.05 -> 0
G10: =B10*0.05 -> 0
G11: =B11*0.05 -> 0
G12: =B12*0.05 -> 0
G13: =B13*0.05 -> 0
G14: =B14*0.05 -> 0
G15: =B15*0.05 -> 0
G16: =B16*0.05 -> 0
G17: =B17*0.05 -> 0
G18: =B18*0.05 -> 0
G19: =B19*0.05 -> 0
... G219: =B219*0.05 -> 0

Sheet Février
B1: Totaux | C1: MÉDIA MULTI-ANNONCEURS | D1: PROMOTIONNEL | E1: DIST. PUBLICITAIRE SOLO | F1: NUMÉRIQUE | G1: APPLICATION | H1: SERVICES IA
A2: Commission | B2: =SUM(G7:G962) -> 59.75 | C2: =SUMIF(F8:F960,"MÉDIA MULTI-ANNONCEURS",G8:G960) -> 59.75 | D2: =SUMIF(F8:F960,"PROMOTIONNEL",G8:G960) -> 0 | E2: =SUMIF(F8:F960,"DIST. PUBLICITAIRE SOLO",G8:G960) -> 0 | F2: =SUMIF(F8:F960,"AGENCE PUB",G8:G960) -> 0 | G2: =SUMIF(F8:F960,"AGENCE WEB",G8:G960) -> 0 | H2: =SUMIF(F8:F960,"SERVICES IA",G8:G960) -> 0
A4: Vente | B4: =SUM(B8:B962) -> 1195 | C4: =SUMIF(F8:F960,"MÉDIA MULTI-ANNONCEURS",B8:B960) -> 1195 | D4: =SUMIF(F8:F960,"PROMOTIONNEL",B8:B960) -> 0 | E4: =SUMIF(F8:F960,"DIST. PUBLICITAIRE SOLO",B8:B960) -> 0 | F4: =SUMIF(F8:F960,"AGENCE PUB",B8:B960) -> 0 | G4: =SUMIF(F8:F960,"AGENCE WEB",B8:B960) -> 0 | H4: =SUMIF(F8:F960,"SERVICES IA",B8:B960) -> 0
A7: CLIENT | B7: TOTAL (AVANT TAXES) | C7: # FACTURE | D7: DATE | E7: REPRÉSENTANT | F7: DÉPARTEMENT | G7: COMMISSION
A8: Chantal Fortier Courtier | B8: 1195 | C8: MTL-001993 | D8: 46080 | E8: Vincent Dagenais | F8: MÉDIA MULTI-ANNONCEURS | G8: =B8*0.05 -> 59.75
G9: =B9*0.05 -> 0
G10: =B10*0.05 -> 0
G11: =B11*0.05 -> 0
G12: =B12*0.05 -> 0
G13: =B13*0.05 -> 0
G14: =B14*0.05 -> 0
G15: =B15*0.05 -> 0
G16: =B16*0.05 -> 0
G17: =B17*0.05 -> 0
G18: =B18*0.05 -> 0
G19: =B19*0.05 -> 0
G20: =B20*0.05 -> 0
... G219: =B219*0.05 -> 0

Sheet Mars
B1: Totaux | C1: MÉDIA MULTI-ANNONCEURS | D1: PROMOTIONNEL | E1: DIST. PUBLICITAIRE SOLO | F1: NUMÉRIQUE | G1: APPLICATION | H1: SERVICES IA
A2: Commission | B2: =SUM(G7:G962) -> 152 | C2: =SUMIF(F8:F960,"MÉDIA MULTI-ANNONCEURS",G8:G960) -> 59.75 | D2: =SUMIF(F8:F960,"PROMOTIONNEL",G8:G960) -> 0 | E2: =SUMIF(F8:F960,"DIST. PUBLICITAIRE SOLO",G8:G960) -> 71.75 | F2: =SUMIF(F8:F960,"AGENCE PUB",G8:G960) -> 20.5 | G2: =SUMIF(F8:F960,"AGENCE WEB",G8:G960) -> 0 | H2: =SUMIF(F8:F960,"SERVICES IA",G8:G960) -> 0
A4: Vente | B4: =SUM(B8:B962) -> 3040 | C4: =SUMIF(F8:F960,"MÉDIA MULTI-ANNONCEURS",B8:B960) -> 1195 | D4: =SUMIF(F8:F960,"PROMOTIONNEL",B8:B960) -> 0 | E4: =SUMIF(F8:F960,"DIST. PUBLICITAIRE SOLO",B8:B960) -> 1435 | F4: =SUMIF(F8:F960,"AGENCE PUB",B8:B960) -> 410 | G4: =SUMIF(F8:F960,"AGENCE WEB",B8:B960) -> 0 | H4: =SUMIF(F8:F960,"SERVICES IA",B8:B960) -> 0
A7: CLIENT | B7: TOTAL (AVANT TAXES) | C7: # FACTURE | D7: DATE | E7: REPRÉSENTANT | F7: DÉPARTEMENT | G7: COMMISSION
A8: Chantal Fortier Courtier | B8: 1195 | C8: MTL-002041 | D8: 46094 | E8: Vincent Dagenais | F8: MÉDIA MULTI-ANNONCEURS | G8: =B8*0.05 -> 59.75
A9: Benjamin Rousseau Courtier Immobilier Résidentiel | B9: 1435 | C9: MTL-002079 | D9: 46108 | E9: Vincent Dagenais | F9: DIST. PUBLICITAIRE SOLO | G9: =B9*0.05 -> 71.75
A10: Isabelle Gauthier Meloche - IA Groupe Financier | B10: 410 | C10: MTL-002083 | D10: 46111 | E10: Vincent Dagenais | F10: AGENCE PUB | G10: =B10*0.05 -> 20.5
G11: =B11*0.05 -> 0
G12: =B12*0.05 -> 0
G13: =B13*0.05 -> 0
G14: =B14*0.05 -> 0
G15: =B15*0.05 -> 0
G16: =B16*0.05 -> 0
G17: =B17*0.05 -> 0
G18: =B18*0.05 -> 0
G19: =B19*0.05 -> 0
G20: =B20*0.05 -> 0
G21: =B21*0.05 -> 0
G22: =B22*0.05 -> 0
... G212: =B212*0.05 -> 0

Sheet Avril
B1: Totaux | C1: MÉDIA MULTI-ANNONCEURS | D1: PROMOTIONNEL | E1: DIST. PUBLICITAIRE SOLO | F1: NUMÉRIQUE | G1: APPLICATION | H1: SERVICES IA
A2: Commission | B2: =SUM(G7:G962) -> 192.25 | C2: =SUMIF(F8:F960,"MÉDIA MULTI-ANNONCEURS",G8:G960) -> 184.25 | D2: =SUMIF(F8:F960,"PROMOTIONNEL",G8:G960) -> 0 | E2: =SUMIF(F8:F960,"DIST. PUBLICITAIRE SOLO",G8:G960) -> 0 | F2: =SUMIF(F8:F960,"AGENCE PUB",G8:G960) -> 8 | G2: =SUMIF(F8:F960,"AGENCE WEB",G8:G960) -> 0 | H2: =SUMIF(F8:F960,"SERVICES IA",G8:G960) -> 0
A4: Vente | B4: =SUM(B8:B962) -> 3845 | C4: =SUMIF(F8:F960,"MÉDIA MULTI-ANNONCEURS",B8:B960) -> 3685 | D4: =SUMIF(F8:F960,"PROMOTIONNEL",B8:B960) -> 0 | E4: =SUMIF(F8:F960,"DIST. PUBLICITAIRE SOLO",B8:B960) -> 0 | F4: =SUMIF(F8:F960,"AGENCE PUB",B8:B960) -> 160 | G4: =SUMIF(F8:F960,"AGENCE WEB",B8:B960) -> 0 | H4: =SUMIF(F8:F960,"SERVICES IA",B8:B960) -> 0
A7: CLIENT | B7: TOTAL (AVANT TAXES) | C7: # FACTURE | D7: DATE | E7: REPRÉSENTANT | F7: DÉPARTEMENT | G7: COMMISSION
A8: Chantal Fortier Courtier | B8: 1195 | C8: MTL-002130 | D8: 46125 | E8: Vincent Dagenais | F8: MÉDIA MULTI-ANNONCEURS | G8: =B8*0.05 -> 59.75
A9: Les industries Pronet Inc | B9: 1245 | C9: MTL-002176 | D9: 46135 | E9: Vincent Dagenais | F9: MÉDIA MULTI-ANNONCEURS | G9: =B9*0.05 -> 62.25
A10: Les industries Pronet Inc | B10: 160 | C10: MTL-002175 | D10: 46135 | E10: Vincent Dagenais | F10: AGENCE PUB | G10: =B10*0.05 -> 8
A11: Qualité Aeration INC | B11: 1245 | C11: MTL-002173 | D11: 46134 | E11: Vincent Dagenais | F11: MÉDIA MULTI-ANNONCEURS | G11: =B11*0.05 -> 62.25
G12: =B12*0.05 -> 0
G13: =B13*0.05 -> 0
G14: =B14*0.05 -> 0
G15: =B15*0.05 -> 0
G16: =B16*0.05 -> 0
G17: =B17*0.05 -> 0
G18: =B18*0.05 -> 0
G19: =B19*0.05 -> 0
G20: =B20*0.05 -> 0
G21: =B21*0.05 -> 0
G22: =B22*0.05 -> 0
G23: =B23*0.05 -> 0
... G234: =B234*0.05 -> 0

Sheet Mai
B1: Totaux | C1: MÉDIA MULTI-ANNONCEURS | D1: PROMOTIONNEL | E1: DIST. PUBLICITAIRE SOLO | F1: NUMÉRIQUE | G1: APPLICATION | H1: SERVICES IA
A2: Commission | B2: =SUM(G7:G962) -> 0 | C2: =SUMIF(F8:F960,"MÉDIA MULTI-ANNONCEURS",G8:G960) -> 0 | D2: =SUMIF(F8:F960,"PROMOTIONNEL",G8:G960) -> 0 | E2: =SUMIF(F8:F960,"DIST. PUBLICITAIRE SOLO",G8:G960) -> 0 | F2: =SUMIF(F8:F960,"AGENCE PUB",G8:G960) -> 0 | G2: =SUMIF(F8:F960,"AGENCE WEB",G8:G960) -> 0 | H2: =SUMIF(F8:F960,"SERVICES IA",G8:G960) -> 0
A4: Vente | B4: =SUM(B8:B962) -> 0 | C4: =SUMIF(F8:F960,"MÉDIA MULTI-ANNONCEURS",B8:B960) -> 0 | D4: =SUMIF(F8:F960,"PROMOTIONNEL",B8:B960) -> 0 | E4: =SUMIF(F8:F960,"DIST. PUBLICITAIRE SOLO",B8:B960) -> 0 | F4: =SUMIF(F8:F960,"AGENCE PUB",B8:B960) -> 0 | G4: =SUMIF(F8:F960,"AGENCE WEB",B8:B960) -> 0 | H4: =SUMIF(F8:F960,"SERVICES IA",B8:B960) -> 0
A7: CLIENT | B7: TOTAL (AVANT TAXES) | C7: # FACTURE | D7: DATE | E7: REPRÉSENTANT | F7: DÉPARTEMENT | G7: COMMISSION
G8: =B8*0.05 -> 0
G9: =B9*0.05 -> 0
G10: =B10*0.05 -> 0
G11: =B11*0.05 -> 0
G12: =B12*0.05 -> 0
G13: =B13*0.05 -> 0
G14: =B14*0.05 -> 0
G15: =B15*0.05 -> 0
G16: =B16*0.05 -> 0
G17: =B17*0.05 -> 0
G18: =B18*0.05 -> 0
G19: =B19*0.05 -> 0
... G215: =B215*0.05 -> 0

Sheet Juin
B1: Totaux | C1: MÉDIA MULTI-ANNONCEURS | D1: PROMOTIONNEL | E1: DIST. PUBLICITAIRE SOLO | F1: NUMÉRIQUE | G1: APPLICATION | H1: SERVICES IA
A2: Commission | B2: =SUM(G7:G962) -> 0 | C2: =SUMIF(F8:F960,"MÉDIA MULTI-ANNONCEURS",G8:G960) -> 0 | D2: =SUMIF(F8:F960,"PROMOTIONNEL",G8:G960) -> 0 | E2: =SUMIF(F8:F960,"DIST. PUBLICITAIRE SOLO",G8:G960) -> 0 | F2: =SUMIF(F8:F960,"AGENCE PUB",G8:G960) -> 0 | G2: =SUMIF(F8:F960,"AGENCE WEB",G8:G960) -> 0 | H2: =SUMIF(F8:F960,"SERVICES IA",G8:G960) -> 0
A4: Vente | B4: =SUM(B8:B962) -> 0 | C4: =SUMIF(F8:F960,"MÉDIA MULTI-ANNONCEURS",B8:B960) -> 0 | D4: =SUMIF(F8:F960,"PROMOTIONNEL",B8:B960) -> 0 | E4: =SUMIF(F8:F960,"DIST. PUBLICITAIRE SOLO",B8:B960) -> 0 | F4: =SUMIF(F8:F960,"AGENCE PUB",B8:B960) -> 0 | G4: =SUMIF(F8:F960,"AGENCE WEB",B8:B960) -> 0 | H4: =SUMIF(F8:F960,"SERVICES IA",B8:B960) -> 0
A7: CLIENT | B7: TOTAL (AVANT TAXES) | C7: # FACTURE | D7: DATE | E7: REPRÉSENTANT | F7: DÉPARTEMENT | G7: COMMISSION
G8: =B8*0.05 -> 0
G9: =B9*0.05 -> 0
G10: =B10*0.05 -> 0
G11: =B11*0.05 -> 0
G12: =B12*0.05 -> 0
G13: =B13*0.05 -> 0
G14: =B14*0.05 -> 0
G15: =B15*0.05 -> 0
G16: =B16*0.05 -> 0
G17: =B17*0.05 -> 0
G18: =B18*0.05 -> 0
G19: =B19*0.05 -> 0
... G218: =B218*0.05 -> 0

Sheet Juillet
B1: Totaux | C1: MÉDIA MULTI-ANNONCEURS | D1: PROMOTIONNEL | E1: DIST. PUBLICITAIRE SOLO | F1: NUMÉRIQUE | G1: APPLICATION | H1: SERVICES IA
A2: Commission | B2: =SUM(G7:G962) -> 0 | C2: =SUMIF(F8:F960,"MÉDIA MULTI-ANNONCEURS",G8:G960) -> 0 | D2: =SUMIF(F8:F960,"PROMOTIONNEL",G8:G960) -> 0 | E2: =SUMIF(F8:F960,"DIST. PUBLICITAIRE SOLO",G8:G960) -> 0 | F2: =SUMIF(F8:F960,"AGENCE PUB",G8:G960) -> 0 | G2: =SUMIF(F8:F960,"AGENCE WEB",G8:G960) -> 0 | H2: =SUMIF(F8:F960,"SERVICES IA",G8:G960) -> 0
A4: Vente | B4: =SUM(B8:B962) -> 0 | C4: =SUMIF(F8:F960,"MÉDIA MULTI-ANNONCEURS",B8:B960) -> 0 | D4: =SUMIF(F8:F960,"PROMOTIONNEL",B8:B960) -> 0 | E4: =SUMIF(F8:F960,"DIST. PUBLICITAIRE SOLO",B8:B960) -> 0 | F4: =SUMIF(F8:F960,"AGENCE PUB",B8:B960) -> 0 | G4: =SUMIF(F8:F960,"AGENCE WEB",B8:B960) -> 0 | H4: =SUMIF(F8:F960,"SERVICES IA",B8:B960) -> 0
A7: CLIENT | B7: TOTAL (AVANT TAXES) | C7: # FACTURE | D7: DATE | E7: REPRÉSENTANT | F7: DÉPARTEMENT | G7: COMMISSION
G8: =B8*0.05 -> 0
G9: =B9*0.05 -> 0
G10: =B10*0.05 -> 0
G11: =B11*0.05 -> 0
G12: =B12*0.05 -> 0
G13: =B13*0.05 -> 0
G14: =B14*0.05 -> 0
G15: =B15*0.05 -> 0
G16: =B16*0.05 -> 0
G17: =B17*0.05 -> 0
G18: =B18*0.05 -> 0
G19: =B19*0.05 -> 0
... G218: =B218*0.05 -> 0

Sheet Août
B1: Totaux | C1: MÉDIA MULTI-ANNONCEURS | D1: PROMOTIONNEL | E1: DIST. PUBLICITAIRE SOLO | F1: NUMÉRIQUE | G1: APPLICATION | H1: SERVICES IA
A2: Commission | B2: =SUM(G7:G962) -> 0 | C2: =SUMIF(F8:F960,"MÉDIA MULTI-ANNONCEURS",G8:G960) -> 0 | D2: =SUMIF(F8:F960,"PROMOTIONNEL",G8:G960) -> 0 | E2: =SUMIF(F8:F960,"DIST. PUBLICITAIRE SOLO",G8:G960) -> 0 | F2: =SUMIF(F8:F960,"AGENCE PUB",G8:G960) -> 0 | G2: =SUMIF(F8:F960,"AGENCE WEB",G8:G960) -> 0 | H2: =SUMIF(F8:F960,"SERVICES IA",G8:G960) -> 0
A4: Vente | B4: =SUM(B8:B962) -> 0 | C4: =SUMIF(F8:F960,"MÉDIA MULTI-ANNONCEURS",B8:B960) -> 0 | D4: =SUMIF(F8:F960,"PROMOTIONNEL",B8:B960) -> 0 | E4: =SUMIF(F8:F960,"DIST. PUBLICITAIRE SOLO",B8:B960) -> 0 | F4: =SUMIF(F8:F960,"AGENCE PUB",B8:B960) -> 0 | G4: =SUMIF(F8:F960,"AGENCE WEB",B8:B960) -> 0 | H4: =SUMIF(F8:F960,"SERVICES IA",B8:B960) -> 0
A7: CLIENT | B7: TOTAL (AVANT TAXES) | C7: # FACTURE | D7: DATE | E7: REPRÉSENTANT | F7: DÉPARTEMENT | G7: COMMISSION
G8: =B8*0.05 -> 0
G9: =B9*0.05 -> 0
G10: =B10*0.05 -> 0
G11: =B11*0.05 -> 0
G12: =B12*0.05 -> 0
G13: =B13*0.05 -> 0
G14: =B14*0.05 -> 0
G15: =B15*0.05 -> 0
G16: =B16*0.05 -> 0
G17: =B17*0.05 -> 0
G18: =B18*0.05 -> 0
G19: =B19*0.05 -> 0
... G216: =B216*0.05 -> 0

Sheet Septembre
B1: Totaux | C1: MÉDIA MULTI-ANNONCEURS | D1: PROMOTIONNEL | E1: DIST. PUBLICITAIRE SOLO | F1: NUMÉRIQUE | G1: APPLICATION | H1: SERVICES IA
A2: Commission | B2: =SUM(G7:G962) -> 0 | C2: =SUMIF(F8:F960,"MÉDIA MULTI-ANNONCEURS",G8:G960) -> 0 | D2: =SUMIF(F8:F960,"PROMOTIONNEL",G8:G960) -> 0 | E2: =SUMIF(F8:F960,"DIST. PUBLICITAIRE SOLO",G8:G960) -> 0 | F2: =SUMIF(F8:F960,"AGENCE PUB",G8:G960) -> 0 | G2: =SUMIF(F8:F960,"AGENCE WEB",G8:G960) -> 0 | H2: =SUMIF(F8:F960,"SERVICES IA",G8:G960) -> 0
A4: Vente | B4: =SUM(B8:B962) -> 0 | C4: =SUMIF(F8:F960,"MÉDIA MULTI-ANNONCEURS",B8:B960) -> 0 | D4: =SUMIF(F8:F960,"PROMOTIONNEL",B8:B960) -> 0 | E4: =SUMIF(F8:F960,"DIST. PUBLICITAIRE SOLO",B8:B960) -> 0 | F4: =SUMIF(F8:F960,"AGENCE PUB",B8:B960) -> 0 | G4: =SUMIF(F8:F960,"AGENCE WEB",B8:B960) -> 0 | H4: =SUMIF(F8:F960,"SERVICES IA",B8:B960) -> 0
A7: CLIENT | B7: TOTAL (AVANT TAXES) | C7: # FACTURE | D7: DATE | E7: REPRÉSENTANT | F7: DÉPARTEMENT | G7: COMMISSION
G8: =B8*0.05 -> 0
G9: =B9*0.05 -> 0
G10: =B10*0.05 -> 0
G11: =B11*0.05 -> 0
G12: =B12*0.05 -> 0
G13: =B13*0.05 -> 0
G14: =B14*0.05 -> 0
G15: =B15*0.05 -> 0
G16: =B16*0.05 -> 0
G17: =B17*0.05 -> 0
G18: =B18*0.05 -> 0
G19: =B19*0.05 -> 0
... G219: =B219*0.05 -> 0

Sheet Octobre
B1: Totaux | C1: MÉDIA MULTI-ANNONCEURS | D1: PROMOTIONNEL | E1: DIST. PUBLICITAIRE SOLO | F1: NUMÉRIQUE | G1: APPLICATION | H1: SERVICES IA
A2: Commission | B2: =SUM(G7:G962) -> 0 | C2: =SUMIF(F8:F960,"MÉDIA MULTI-ANNONCEURS",G8:G960) -> 0 | D2: =SUMIF(F8:F960,"PROMOTIONNEL",G8:G960) -> 0 | E2: =SUMIF(F8:F960,"DIST. PUBLICITAIRE SOLO",G8:G960) -> 0 | F2: =SUMIF(F8:F960,"AGENCE PUB",G8:G960) -> 0 | G2: =SUMIF(F8:F960,"AGENCE WEB",G8:G960) -> 0 | H2: =SUMIF(F8:F960,"SERVICES IA",G8:G960) -> 0
A4: Vente | B4: =SUM(B8:B962) -> 0 | C4: =SUMIF(F8:F960,"MÉDIA MULTI-ANNONCEURS",B8:B960) -> 0 | D4: =SUMIF(F8:F960,"PROMOTIONNEL",B8:B960) -> 0 | E4: =SUMIF(F8:F960,"DIST. PUBLICITAIRE SOLO",B8:B960) -> 0 | F4: =SUMIF(F8:F960,"AGENCE PUB",B8:B960) -> 0 | G4: =SUMIF(F8:F960,"AGENCE WEB",B8:B960) -> 0 | H4: =SUMIF(F8:F960,"SERVICES IA",B8:B960) -> 0
A7: CLIENT | B7: TOTAL (AVANT TAXES) | C7: # FACTURE | D7: DATE | E7: REPRÉSENTANT | F7: DÉPARTEMENT | G7: COMMISSION
G8: =B8*0.05 -> 0
G9: =B9*0.05 -> 0
G10: =B10*0.05 -> 0
G11: =B11*0.05 -> 0
G12: =B12*0.05 -> 0
G13: =B13*0.05 -> 0
G14: =B14*0.05 -> 0
G15: =B15*0.05 -> 0
G16: =B16*0.05 -> 0
G17: =B17*0.05 -> 0
G18: =B18*0.05 -> 0
G19: =B19*0.05 -> 0
... G230: =B230*0.05 -> 0

Sheet Novembre
B1: Totaux | C1: MÉDIA MULTI-ANNONCEURS | D1: PROMOTIONNEL | E1: DIST. PUBLICITAIRE SOLO | F1: NUMÉRIQUE | G1: APPLICATION | H1: SERVICES IA
A2: Commission | B2: =SUM(G7:G962) -> 0 | C2: =SUMIF(F8:F960,"MÉDIA MULTI-ANNONCEURS",G8:G960) -> 0 | D2: =SUMIF(F8:F960,"PROMOTIONNEL",G8:G960) -> 0 | E2: =SUMIF(F8:F960,"DIST. PUBLICITAIRE SOLO",G8:G960) -> 0 | F2: =SUMIF(F8:F960,"AGENCE PUB",G8:G960) -> 0 | G2: =SUMIF(F8:F960,"AGENCE WEB",G8:G960) -> 0 | H2: =SUMIF(F8:F960,"SERVICES IA",G8:G960) -> 0
A4: Vente | B4: =SUM(B8:B962) -> 0 | C4: =SUMIF(F8:F960,"MÉDIA MULTI-ANNONCEURS",B8:B960) -> 0 | D4: =SUMIF(F8:F960,"PROMOTIONNEL",B8:B960) -> 0 | E4: =SUMIF(F8:F960,"DIST. PUBLICITAIRE SOLO",B8:B960) -> 0 | F4: =SUMIF(F8:F960,"AGENCE PUB",B8:B960) -> 0 | G4: =SUMIF(F8:F960,"AGENCE WEB",B8:B960) -> 0 | H4: =SUMIF(F8:F960,"SERVICES IA",B8:B960) -> 0
A7: CLIENT | B7: TOTAL (AVANT TAXES) | C7: # FACTURE | D7: DATE | E7: REPRÉSENTANT | F7: DÉPARTEMENT | G7: COMMISSION
G8: =B8*0.05 -> 0
G9: =B9*0.05 -> 0
G10: =B10*0.05 -> 0
G11: =B11*0.05 -> 0
G12: =B12*0.05 -> 0
G13: =B13*0.05 -> 0
G14: =B14*0.05 -> 0
G15: =B15*0.05 -> 0
G16: =B16*0.05 -> 0
G17: =B17*0.05 -> 0
G18: =B18*0.05 -> 0
G19: =B19*0.05 -> 0
... G212: =B212*0.05 -> 0

Sheet Décembre
B1: Totaux | C1: MÉDIA MULTI-ANNONCEURS | D1: PROMOTIONNEL | E1: DIST. PUBLICITAIRE SOLO | F1: NUMÉRIQUE | G1: APPLICATION | H1: SERVICES IA
A2: Commission | B2: =SUM(G7:G962) -> 0 | C2: =SUMIF(F8:F960,"MÉDIA MULTI-ANNONCEURS",G8:G960) -> 0 | D2: =SUMIF(F8:F960,"PROMOTIONNEL",G8:G960) -> 0 | E2: =SUMIF(F8:F960,"DIST. PUBLICITAIRE SOLO",G8:G960) -> 0 | F2: =SUMIF(F8:F960,"AGENCE PUB",G8:G960) -> 0 | G2: =SUMIF(F8:F960,"AGENCE WEB",G8:G960) -> 0 | H2: =SUMIF(F8:F960,"SERVICES IA",G8:G960) -> 0
A4: Vente | B4: =SUM(B8:B962) -> 0 | C4: =SUMIF(F8:F960,"MÉDIA MULTI-ANNONCEURS",B8:B960) -> 0 | D4: =SUMIF(F8:F960,"PROMOTIONNEL",B8:B960) -> 0 | E4: =SUMIF(F8:F960,"DIST. PUBLICITAIRE SOLO",B8:B960) -> 0 | F4: =SUMIF(F8:F960,"AGENCE PUB",B8:B960) -> 0 | G4: =SUMIF(F8:F960,"AGENCE WEB",B8:B960) -> 0 | H4: =SUMIF(F8:F960,"SERVICES IA",B8:B960) -> 0
A7: CLIENT | B7: TOTAL (AVANT TAXES) | C7: # FACTURE | D7: DATE | E7: REPRÉSENTANT | F7: DÉPARTEMENT | G7: COMMISSION
G8: =B8*0.05 -> 0
G9: =B9*0.05 -> 0
G10: =B10*0.05 -> 0
G11: =B11*0.05 -> 0
G12: =B12*0.05 -> 0
G13: =B13*0.05 -> 0
G14: =B14*0.05 -> 0
G15: =B15*0.05 -> 0
G16: =B16*0.05 -> 0
G17: =B17*0.05 -> 0
G18: =B18*0.05 -> 0
G19: =B19*0.05 -> 0
... G212: =B212*0.05 -> 0
